determined_deploy/__init__.py
determined_deploy/__version__.py
determined_deploy-0.22.2.dist-info/METADATA
determined_deploy-0.22.2.dist-info/WHEEL
determined_deploy-0.22.2.dist-info/top_level.txt
determined_deploy-0.22.2.dist-info/RECORD
