Metadata-Version: 2.1
Name: determined-deploy
Version: 0.22.2
Summary: Determined Deep Learning Training Platform
Home-page: https://determined.ai/
Author: Determined AI
Author-email: hello@determined.ai
License: Apache License 2.0
Classifier: License :: OSI Approved :: Apache Software License
Requires-Python: >=3.6
Requires-Dist: determined (==0.22.2)
